{"code":200,"relatedVideos":null,"playlist":{"id":6876152675,"name":"FM刘群音乐之声","coverImgId":109951166364914910,"coverImgUrl":"https://p1.music.126.net/TUihQh6D9cwKPe1S0mOKeA==/109951166364914915.jpg","coverImgId_str":"109951166364914915","adType":0,"userId":20226098,"createTime":1626964418634,"status":0,"opRecommend":false,"highQuality":false,"newImported":false,"updateTime":1657549019076,"trackCount":6,"specialType":300,"privacy":0,"trackUpdateTime":1657549270325,"commentThreadId":"A_PL_0_6876152675","playCount":5681,"trackNumberUpdateTime":1657549019076,"subscribedCount":67,"cloudTrackCount":0,"ordered":true,"description":"2022/07/13 主题：我与我周旋久#朗朗","tags":["榜单"],"updateFrequency":null,"backgroundCoverId":0,"backgroundCoverUrl":null,"titleImage":0,"titleImageUrl":null,"englishTitle":null,"officialPlaylistType":null,"subscribers":[{"defaultAvatar":false,"province":110000,"authStatus":0,"followed":false,"avatarUrl":"http://p1.music.126.net/tefHW4i8bJyKO3etRj7jRQ==/7820826209544414.jpg","accountStatus":0,"gender":1,"city":110101,"birthday":0,"userId":83715386,"userType":0,"nickname":"cidgur","signature":"D key","description":"","detailDescription":"","avatarImgId":7820826209544414,"backgroundImgId":2002210674180203,"backgroundUrl":"http://p1.music.126.net/bmA_ablsXpq3Tk9HlEg9sA==/2002210674180203.jpg","authority":0,"mutual":false,"expertTags":null,"experts":null,"djStatus":0,"vipType":11,"remarkName":null,"authenticationTypes":0,"avatarDetail":null,"avatarImgIdStr":"7820826209544414","backgroundImgIdStr":"2002210674180203","anchor":false},{"defaultAvatar":false,"province":210000,"authStatus":0,"followed":false,"avatarUrl":"http://p1.music.126.net/fVAlyr00y_bRTniMqtNs-Q==/5823013580702205.jpg","accountStatus":0,"gender":1,"city":210100,"birthday":0,"userId":3508301,"userType":0,"nickname":"清淺同學","signature":"一个脱离了高级趣味的人。","description":"","detailDescription":"","avatarImgId":5823013580702205,"backgroundImgId":19210667160902320,"backgroundUrl":"http://p1.music.126.net/h7_p0rtRoF3vGZuA9zUxyw==/19210667160902318.jpg","authority":0,"mutual":false,"expertTags":null,"experts":null,"djStatus":0,"vipType":11,"remarkName":null,"authenticationTypes":0,"avatarDetail":null,"avatarImgIdStr":"5823013580702205","backgroundImgIdStr":"19210667160902318","anchor":false},{"defaultAvatar":false,"province":220000,"authStatus":0,"followed":false,"avatarUrl":"http://p1.music.126.net/AQu_pdt-qNxxq68SUqXWaA==/109951166656295944.jpg","accountStatus":0,"gender":2,"city":220100,"birthday":0,"userId":643492877,"userType":0,"nickname":"缅因猫_zRkW","signature":"","description":"","detailDescription":"","avatarImgId":109951166656295940,"backgroundImgId":109951165489528860,"backgroundUrl":"http://p1.music.126.net/RunfGK73E-6SIPGK_GxsBA==/109951165489528866.jpg","authority":0,"mutual":false,"expertTags":null,"experts":null,"djStatus":0,"vipType":11,"remarkName":null,"authenticationTypes":0,"avatarDetail":null,"avatarImgIdStr":"109951166656295944","backgroundImgIdStr":"109951165489528866","anchor":false,"avatarImgId_str":"109951166656295944"},{"defaultAvatar":false,"province":210000,"authStatus":0,"followed":false,"avatarUrl":"http://p1.music.126.net/7k1yuV45PZnqs7Udf8_Cag==/109951163756487154.jpg","accountStatus":0,"gender":2,"city":210200,"birthday":0,"userId":554972931,"userType":0,"nickname":"好好学习努力暴富","signature":"业余击剑运动员/大连人球迷/费德勒球迷","description":"","detailDescription":"","avatarImgId":109951163756487150,"backgroundImgId":109951162868128400,"backgroundUrl":"http://p1.music.126.net/2zSNIqTcpHL2jIvU6hG0EA==/109951162868128395.jpg","authority":0,"mutual":false,"expertTags":null,"experts":null,"djStatus":0,"vipType":11,"remarkName":null,"authenticationTypes":0,"avatarDetail":null,"avatarImgIdStr":"109951163756487154","backgroundImgIdStr":"109951162868128395","anchor":false,"avatarImgId_str":"109951163756487154"},{"defaultAvatar":false,"province":230000,"authStatus":0,"followed":false,"avatarUrl":"http://p1.music.126.net/1-dBtnvlNjgC8WkfsqpKlQ==/109951167543733315.jpg","accountStatus":0,"gender":0,"city":230100,"birthday":0,"userId":5193884832,"userType":0,"nickname":"cello华风","signature":"孤独的人呐，我带上你走","description":"","detailDescription":"","avatarImgId":109951167543733310,"backgroundImgId":109951167550273470,"backgroundUrl":"http://p1.music.126.net/gged9lZ1MUvjY_h_Vgpehg==/109951167550273472.jpg","authority":0,"mutual":false,"expertTags":null,"experts":null,"djStatus":0,"vipType":11,"remarkName":null,"authenticationTypes":0,"avatarDetail":null,"avatarImgIdStr":"109951167543733315","backgroundImgIdStr":"109951167550273472","anchor":false,"avatarImgId_str":"109951167543733315"},{"defaultAvatar":false,"province":1000000,"authStatus":0,"followed":false,"avatarUrl":"http://p1.music.126.net/PW7W-MQ3M86pl8o7a2DHCA==/109951167108095958.jpg","accountStatus":0,"gender":2,"city":1007700,"birthday":0,"userId":1552567574,"userType":0,"nickname":"KoyarH","signature":"在那座岛屿","description":"","detailDescription":"","avatarImgId":109951167108095950,"backgroundImgId":109951165395733630,"backgroundUrl":"http://p1.music.126.net/JoV68ORMXbVRqYMDNp28GA==/109951165395733633.jpg","authority":0,"mutual":false,"expertTags":null,"experts":null,"djStatus":0,"vipType":11,"remarkName":null,"authenticationTypes":0,"avatarDetail":null,"avatarImgIdStr":"109951167108095958","backgroundImgIdStr":"109951165395733633","anchor":false,"avatarImgId_str":"109951167108095958"},{"defaultAvatar":false,"province":120000,"authStatus":0,"followed":false,"avatarUrl":"http://p1.music.126.net/JJB6oDJNnmoRXjrdummm6g==/109951164757578418.jpg","accountStatus":0,"gender":0,"city":120101,"birthday":0,"userId":1949412838,"userType":0,"nickname":"煮酒5233","signature":"","description":"","detailDescription":"","avatarImgId":109951164757578420,"backgroundImgId":109951164870122300,"backgroundUrl":"http://p1.music.126.net/zC-COMo-A7Msa_XQYZY0uQ==/109951164870122312.jpg","authority":0,"mutual":false,"expertTags":null,"experts":null,"djStatus":0,"vipType":0,"remarkName":null,"authenticationTypes":0,"avatarDetail":null,"avatarImgIdStr":"109951164757578418","backgroundImgIdStr":"109951164870122312","anchor":false,"avatarImgId_str":"109951164757578418"},{"defaultAvatar":false,"province":500000,"authStatus":0,"followed":false,"avatarUrl":"http://p1.music.126.net/EGl1XG8YJWf_5yeP2AyclA==/109951163881144487.jpg","accountStatus":0,"gender":0,"city":500101,"birthday":0,"userId":133688772,"userType":0,"nickname":"阿达达嘎","signature":"鸿飞那复计东西","description":"","detailDescription":"","avatarImgId":109951163881144480,"backgroundImgId":109951166361786340,"backgroundUrl":"http://p1.music.126.net/fjZvnTBqCjV3y6a8GEu5jQ==/109951166361786340.jpg","authority":0,"mutual":false,"expertTags":null,"experts":null,"djStatus":0,"vipType":11,"remarkName":null,"authenticationTypes":0,"avatarDetail":null,"avatarImgIdStr":"109951163881144487","backgroundImgIdStr":"109951166361786340","anchor":false,"avatarImgId_str":"109951163881144487"}],"subscribed":false,"creator":{"defaultAvatar":false,"province":310000,"authStatus":0,"followed":false,"avatarUrl":"http://p1.music.126.net/dRf7W7t0MB6bzfYGjskwoA==/6017627139384597.jpg","accountStatus":0,"gender":1,"city":310101,"birthday":0,"userId":20226098,"userType":0,"nickname":"大藏藏","signature":"oh my international cool playboy!","description":"","detailDescription":"","avatarImgId":6017627139384597,"backgroundImgId":109951166202689170,"backgroundUrl":"http://p1.music.126.net/lt1K0huJagqDwbrmkUcYPA==/109951166202689168.jpg","authority":0,"mutual":false,"expertTags":null,"experts":null,"djStatus":0,"vipType":11,"remarkName":null,"authenticationTypes":0,"avatarDetail":null,"avatarImgIdStr":"6017627139384597","backgroundImgIdStr":"109951166202689168","anchor":false},"tracks":[{"name":"生活的诗意","id":1465257532,"pst":0,"t":0,"ar":[{"id":4722,"name":"彭坦","tns":[],"alias":[]}],"alia":[],"pop":55,"st":0,"rt":"","fee":8,"v":12,"crbt":null,"cf":"","al":{"id":92932272,"name":"子夜集","picUrl":"http://p4.music.126.net/nQRhEzr6CNuq5hD7xcH94g==/109951165165184509.jpg","tns":[],"pic_str":"109951165165184509","pic":109951165165184510},"dt":268134,"h":{"br":320001,"fid":0,"size":10728011,"vd":-39548,"sr":44100},"m":{"br":192001,"fid":0,"size":6436824,"vd":-36928,"sr":44100},"l":{"br":128001,"fid":0,"size":4291231,"vd":-35213,"sr":44100},"sq":{"br":1525041,"fid":0,"size":51114625,"vd":-39545,"sr":44100},"hr":null,"a":null,"cd":"01","no":1,"rtUrl":null,"ftype":0,"rtUrls":[],"djId":0,"copyright":0,"s_id":0,"mark":73728,"originCoverType":0,"originSongSimpleData":null,"tagPicList":null,"resourceState":true,"version":12,"songJumpInfo":null,"entertainmentTags":null,"single":0,"noCopyrightRcmd":null,"mv":0,"rtype":0,"rurl":null,"mst":9,"cp":22020,"publishTime":0},{"name":"东湖隧道","id":1465253976,"pst":0,"t":0,"ar":[{"id":4722,"name":"彭坦","tns":[],"alias":[]}],"alia":[],"pop":15,"st":0,"rt":"","fee":8,"v":10,"crbt":null,"cf":"","al":{"id":92932272,"name":"子夜集","picUrl":"http://p4.music.126.net/nQRhEzr6CNuq5hD7xcH94g==/109951165165184509.jpg","tns":[],"pic_str":"109951165165184509","pic":109951165165184510},"dt":352341,"h":{"br":320000,"fid":0,"size":14096762,"vd":-28674,"sr":44100},"m":{"br":192000,"fid":0,"size":8458075,"vd":-26045,"sr":44100},"l":{"br":128000,"fid":0,"size":5638731,"vd":-24287,"sr":44100},"sq":{"br":1394557,"fid":0,"size":61420099,"vd":-28675,"sr":44100},"hr":null,"a":null,"cd":"01","no":5,"rtUrl":null,"ftype":0,"rtUrls":[],"djId":0,"copyright":0,"s_id":0,"mark":73728,"originCoverType":0,"originSongSimpleData":null,"tagPicList":null,"resourceState":true,"version":10,"songJumpInfo":null,"entertainmentTags":null,"single":0,"noCopyrightRcmd":null,"mv":0,"rtype":0,"rurl":null,"mst":9,"cp":22020,"publishTime":0},{"name":"午夜飞船","id":1465253975,"pst":0,"t":0,"ar":[{"id":4722,"name":"彭坦","tns":[],"alias":[]}],"alia":[],"pop":20,"st":0,"rt":"","fee":8,"v":10,"crbt":null,"cf":"","al":{"id":92932272,"name":"子夜集","picUrl":"http://p4.music.126.net/nQRhEzr6CNuq5hD7xcH94g==/109951165165184509.jpg","tns":[],"pic_str":"109951165165184509","pic":109951165165184510},"dt":342002,"h":{"br":320001,"fid":0,"size":13682982,"vd":-22572,"sr":44100},"m":{"br":192001,"fid":0,"size":8209807,"vd":-19896,"sr":44100},"l":{"br":128001,"fid":0,"size":5473219,"vd":-18176,"sr":44100},"sq":{"br":1487212,"fid":0,"size":63578718,"vd":-22570,"sr":44100},"hr":null,"a":null,"cd":"01","no":4,"rtUrl":null,"ftype":0,"rtUrls":[],"djId":0,"copyright":0,"s_id":0,"mark":73728,"originCoverType":0,"originSongSimpleData":null,"tagPicList":null,"resourceState":true,"version":10,"songJumpInfo":null,"entertainmentTags":null,"single":0,"noCopyrightRcmd":null,"mv":0,"rtype":0,"rurl":null,"mst":9,"cp":22020,"publishTime":0},{"name":"听海 (live)","id":187908,"pst":0,"t":0,"ar":[{"id":6460,"name":"张学友","tns":[],"alias":[]}],"alia":[],"pop":100,"st":0,"rt":"600902000005652061","fee":8,"v":28,"crbt":null,"cf":"","al":{"id":19037,"name":"活出生命Live演唱会","picUrl":"http://p4.music.126.net/NUTfjOelDPqV-ITnCyTuNg==/109951166384071636.jpg","tns":[],"pic_str":"109951166384071636","pic":109951166384071630},"dt":287080,"h":{"br":320001,"fid":0,"size":11485562,"vd":-34691,"sr":44100},"m":{"br":192001,"fid":0,"size":6891355,"vd":-32139,"sr":44100},"l":{"br":128001,"fid":0,"size":4594251,"vd":-30559,"sr":44100},"sq":{"br":1610141,"fid":0,"size":57779939,"vd":-34677,"sr":44100},"hr":null,"a":null,"cd":"01","no":5,"rtUrl":null,"ftype":0,"rtUrls":[],"djId":0,"copyright":1,"s_id":0,"mark":8192,"originCoverType":0,"originSongSimpleData":null,"tagPicList":null,"resourceState":true,"version":28,"songJumpInfo":null,"entertainmentTags":null,"single":0,"noCopyrightRcmd":null,"mv":375516,"rtype":0,"rurl":null,"mst":9,"cp":754012,"publishTime":1101830400000},{"name":"拥抱","id":385947,"pst":0,"t":0,"ar":[{"id":13193,"name":"五月天","tns":[],"alias":[]}],"alia":[],"pop":95,"st":0,"rt":"600902000000534576","fee":8,"v":56,"crbt":null,"cf":"","al":{"id":38243,"name":"盛夏光年 电影主题曲概念专辑","picUrl":"http://p3.music.126.net/nz6hFPeMZTo_mQ7tiRzDKA==/109951163093843877.jpg","tns":[],"pic_str":"109951163093843877","pic":109951163093843870},"dt":255733,"h":{"br":320000,"fid":0,"size":10231685,"vd":-42583,"sr":44100},"m":{"br":192000,"fid":0,"size":6139028,"vd":-42583,"sr":44100},"l":{"br":128000,"fid":0,"size":4092700,"vd":-42583,"sr":44100},"sq":{"br":848409,"fid":0,"size":27120827,"vd":-42583,"sr":44100},"hr":null,"a":null,"cd":"1","no":3,"rtUrl":null,"ftype":0,"rtUrls":[],"djId":0,"copyright":0,"s_id":0,"mark":1125899906850816,"originCoverType":1,"originSongSimpleData":null,"tagPicList":null,"resourceState":true,"version":56,"songJumpInfo":null,"entertainmentTags":null,"single":0,"noCopyrightRcmd":null,"mv":10832122,"rtype":0,"rurl":null,"mst":9,"cp":684010,"publishTime":1160668800000},{"name":"散步","id":1334270056,"pst":0,"t":0,"ar":[{"id":4722,"name":"彭坦","tns":[],"alias":[]}],"alia":[],"pop":40,"st":0,"rt":null,"fee":8,"v":10,"crbt":null,"cf":"","al":{"id":74914625,"name":"散步","picUrl":"http://p4.music.126.net/HaRF9X6xHfnmN4oL8dgtqA==/109951163735022976.jpg","tns":[],"pic_str":"109951163735022976","pic":109951163735022980},"dt":315998,"h":{"br":320000,"fid":0,"size":12642264,"vd":-10100,"sr":44100},"m":{"br":192000,"fid":0,"size":7585376,"vd":-7600,"sr":44100},"l":{"br":128000,"fid":0,"size":5056932,"vd":-5899,"sr":44100},"sq":{"br":788058,"fid":0,"size":31128196,"vd":-10100,"sr":44100},"hr":null,"a":null,"cd":"1","no":1,"rtUrl":null,"ftype":0,"rtUrls":[],"djId":0,"copyright":0,"s_id":0,"mark":73728,"originCoverType":0,"originSongSimpleData":null,"tagPicList":null,"resourceState":true,"version":10,"songJumpInfo":null,"entertainmentTags":null,"single":0,"noCopyrightRcmd":null,"mv":0,"rtype":0,"rurl":null,"mst":9,"cp":-1,"publishTime":1545062400000}],"videoIds":null,"videos":null,"trackIds":[{"id":1465257532,"v":13,"t":0,"at":1657549019078,"alg":null,"uid":52272721,"rcmdReason":"","sc":null},{"id":1465253976,"v":11,"t":0,"at":1657549019077,"alg":null,"uid":52272721,"rcmdReason":"","sc":null},{"id":1465253975,"v":11,"t":0,"at":1657549019076,"alg":null,"uid":52272721,"rcmdReason":"","sc":null},{"id":187908,"v":29,"t":0,"at":1657548815240,"alg":null,"uid":296658058,"rcmdReason":"","sc":null},{"id":385947,"v":57,"t":0,"at":1657548795241,"alg":null,"uid":296658058,"rcmdReason":"","sc":null},{"id":1334270056,"v":11,"t":0,"at":1657548786487,"alg":null,"uid":296658058,"rcmdReason":"","sc":null}],"shareCount":5,"commentCount":154,"remixVideo":null,"sharedUsers":[{"defaultAvatar":false,"province":110000,"authStatus":0,"followed":false,"avatarUrl":"http://p1.music.126.net/YiCVHfj_d1iOtIz_RUYEsg==/109951165423851551.jpg","accountStatus":0,"gender":2,"city":110107,"birthday":0,"userId":296658058,"userType":0,"nickname":"吼吼破喉咙","signature":"一面笑的天真无邪，一面看破一切……","description":"","detailDescription":"","avatarImgId":109951165423851550,"backgroundImgId":2002210674180202,"backgroundUrl":"http://p1.music.126.net/pmHS4fcQtcNEGewNb5HRhg==/2002210674180202.jpg","authority":0,"mutual":false,"expertTags":null,"experts":null,"djStatus":0,"vipType":11,"remarkName":null,"authenticationTypes":0,"avatarDetail":null,"avatarImgIdStr":"109951165423851551","backgroundImgIdStr":"2002210674180202","anchor":false,"avatarImgId_str":"109951165423851551"},{"defaultAvatar":false,"province":610000,"authStatus":0,"followed":false,"avatarUrl":"http://p1.music.126.net/-pH51OIr1jvpr_RV2BwHoQ==/109951165631030277.jpg","accountStatus":0,"gender":2,"city":610400,"birthday":0,"userId":100091090,"userType":0,"nickname":"任可爱-","signature":"I think, therefore I am","description":"","detailDescription":"","avatarImgId":109951165631030270,"backgroundImgId":109951165496764200,"backgroundUrl":"http://p1.music.126.net/c_GO6GOAlNn28j4uICNpnQ==/109951165496764196.jpg","authority":0,"mutual":false,"expertTags":null,"experts":null,"djStatus":10,"vipType":11,"remarkName":null,"authenticationTypes":0,"avatarDetail":null,"avatarImgIdStr":"109951165631030277","backgroundImgIdStr":"109951165496764196","anchor":false,"avatarImgId_str":"109951165631030277"}],"historySharedUsers":[{"defaultAvatar":false,"province":0,"authStatus":0,"followed":false,"avatarUrl":"http://p1.music.126.net/JCiDDmCFeD3wIsZIVKMQxA==/18645518184245785.jpg","accountStatus":0,"gender":0,"city":0,"birthday":0,"userId":52272721,"userType":0,"nickname":"迟豫_","signature":null,"description":null,"detailDescription":null,"avatarImgId":0,"backgroundImgId":0,"backgroundUrl":null,"authority":0,"mutual":false,"expertTags":null,"experts":null,"djStatus":0,"vipType":0,"remarkName":null,"authenticationTypes":0,"avatarDetail":null,"avatarImgIdStr":"0","backgroundImgIdStr":"0","anchor":false}],"gradeStatus":"NONE","score":null,"algTags":null},"urls":null,"privileges":[{"id":1465257532,"fee":8,"payed":1,"realPayed":0,"st":0,"pl":999000,"dl":999000,"sp":7,"cp":1,"subp":1,"cs":false,"maxbr":999000,"fl":128000,"pc":null,"toast":false,"flag":4,"paidBigBang":false,"preSell":false,"playMaxbr":999000,"downloadMaxbr":999000,"maxBrLevel":"lossless","playMaxBrLevel":"lossless","downloadMaxBrLevel":"lossless","plLevel":"lossless","dlLevel":"lossless","flLevel":"standard","rscl":null,"freeTrialPrivilege":{"resConsumable":false,"userConsumable":false,"listenType":null},"chargeInfoList":[{"rate":128000,"chargeUrl":null,"chargeMessage":null,"chargeType":0},{"rate":192000,"chargeUrl":null,"chargeMessage":null,"chargeType":1},{"rate":320000,"chargeUrl":null,"chargeMessage":null,"chargeType":1},{"rate":999000,"chargeUrl":null,"chargeMessage":null,"chargeType":1}]},{"id":1465253976,"fee":8,"payed":1,"realPayed":0,"st":0,"pl":999000,"dl":999000,"sp":7,"cp":1,"subp":1,"cs":false,"maxbr":999000,"fl":128000,"pc":null,"toast":false,"flag":4,"paidBigBang":false,"preSell":false,"playMaxbr":999000,"downloadMaxbr":999000,"maxBrLevel":"lossless","playMaxBrLevel":"lossless","downloadMaxBrLevel":"lossless","plLevel":"lossless","dlLevel":"lossless","flLevel":"standard","rscl":null,"freeTrialPrivilege":{"resConsumable":false,"userConsumable":false,"listenType":null},"chargeInfoList":[{"rate":128000,"chargeUrl":null,"chargeMessage":null,"chargeType":0},{"rate":192000,"chargeUrl":null,"chargeMessage":null,"chargeType":1},{"rate":320000,"chargeUrl":null,"chargeMessage":null,"chargeType":1},{"rate":999000,"chargeUrl":null,"chargeMessage":null,"chargeType":1}]},{"id":1465253975,"fee":8,"payed":1,"realPayed":0,"st":0,"pl":999000,"dl":999000,"sp":7,"cp":1,"subp":1,"cs":false,"maxbr":999000,"fl":128000,"pc":null,"toast":false,"flag":4,"paidBigBang":false,"preSell":false,"playMaxbr":999000,"downloadMaxbr":999000,"maxBrLevel":"lossless","playMaxBrLevel":"lossless","downloadMaxBrLevel":"lossless","plLevel":"lossless","dlLevel":"lossless","flLevel":"standard","rscl":null,"freeTrialPrivilege":{"resConsumable":false,"userConsumable":false,"listenType":null},"chargeInfoList":[{"rate":128000,"chargeUrl":null,"chargeMessage":null,"chargeType":0},{"rate":192000,"chargeUrl":null,"chargeMessage":null,"chargeType":1},{"rate":320000,"chargeUrl":null,"chargeMessage":null,"chargeType":1},{"rate":999000,"chargeUrl":null,"chargeMessage":null,"chargeType":1}]},{"id":187908,"fee":8,"payed":1,"realPayed":0,"st":0,"pl":999000,"dl":999000,"sp":7,"cp":1,"subp":1,"cs":false,"maxbr":999000,"fl":128000,"pc":null,"toast":false,"flag":132,"paidBigBang":false,"preSell":false,"playMaxbr":999000,"downloadMaxbr":999000,"maxBrLevel":"lossless","playMaxBrLevel":"lossless","downloadMaxBrLevel":"lossless","plLevel":"lossless","dlLevel":"lossless","flLevel":"standard","rscl":null,"freeTrialPrivilege":{"resConsumable":false,"userConsumable":false,"listenType":null},"chargeInfoList":[{"rate":128000,"chargeUrl":null,"chargeMessage":null,"chargeType":0},{"rate":192000,"chargeUrl":null,"chargeMessage":null,"chargeType":1},{"rate":320000,"chargeUrl":null,"chargeMessage":null,"chargeType":1},{"rate":999000,"chargeUrl":null,"chargeMessage":null,"chargeType":1}]},{"id":385947,"fee":8,"payed":1,"realPayed":0,"st":0,"pl":999000,"dl":999000,"sp":7,"cp":1,"subp":1,"cs":false,"maxbr":999000,"fl":128000,"pc":null,"toast":false,"flag":4,"paidBigBang":false,"preSell":false,"playMaxbr":999000,"downloadMaxbr":999000,"maxBrLevel":"lossless","playMaxBrLevel":"lossless","downloadMaxBrLevel":"lossless","plLevel":"lossless","dlLevel":"lossless","flLevel":"standard","rscl":null,"freeTrialPrivilege":{"resConsumable":false,"userConsumable":false,"listenType":null},"chargeInfoList":[{"rate":128000,"chargeUrl":null,"chargeMessage":null,"chargeType":0},{"rate":192000,"chargeUrl":null,"chargeMessage":null,"chargeType":1},{"rate":320000,"chargeUrl":null,"chargeMessage":null,"chargeType":1},{"rate":999000,"chargeUrl":null,"chargeMessage":null,"chargeType":1}]},{"id":1334270056,"fee":8,"payed":1,"realPayed":0,"st":0,"pl":999000,"dl":999000,"sp":7,"cp":1,"subp":1,"cs":false,"maxbr":999000,"fl":128000,"pc":null,"toast":false,"flag":132,"paidBigBang":false,"preSell":false,"playMaxbr":999000,"downloadMaxbr":999000,"maxBrLevel":"lossless","playMaxBrLevel":"lossless","downloadMaxBrLevel":"lossless","plLevel":"lossless","dlLevel":"lossless","flLevel":"standard","rscl":null,"freeTrialPrivilege":{"resConsumable":false,"userConsumable":false,"listenType":null},"chargeInfoList":[{"rate":128000,"chargeUrl":null,"chargeMessage":null,"chargeType":0},{"rate":192000,"chargeUrl":null,"chargeMessage":null,"chargeType":1},{"rate":320000,"chargeUrl":null,"chargeMessage":null,"chargeType":1},{"rate":999000,"chargeUrl":null,"chargeMessage":null,"chargeType":1}]}],"sharedPrivilege":{"status":"SHARED","usePermission":"NORMAL"},"resEntrance":null}