{"code":200,"relatedVideos":null,"playlist":{"id":6876152675,"name":"FM刘群音乐之声","coverImgId":109951166364914910,"coverImgUrl":"https://p1.music.126.net/TUihQh6D9cwKPe1S0mOKeA==/109951166364914915.jpg","coverImgId_str":"109951166364914915","adType":0,"userId":20226098,"createTime":1626964418634,"status":0,"opRecommend":false,"highQuality":false,"newImported":false,"updateTime":1686063338547,"trackCount":10,"specialType":300,"privacy":0,"trackUpdateTime":1686067652728,"commentThreadId":"A_PL_0_6876152675","playCount":6844,"trackNumberUpdateTime":1686063338547,"subscribedCount":81,"cloudTrackCount":0,"ordered":true,"description":"2023/06/07 主题：宇宙的有趣#想想","tags":["榜单"],"updateFrequency":null,"backgroundCoverId":0,"backgroundCoverUrl":null,"titleImage":0,"titleImageUrl":null,"englishTitle":null,"officialPlaylistType":null,"copied":false,"relateResType":null,"subscribers":[{"defaultAvatar":false,"province":440000,"authStatus":0,"followed":false,"avatarUrl":"http://p1.music.126.net/ZgXig9k9tA0G9mS09IK7oQ==/6671836558105156.jpg","accountStatus":0,"gender":1,"city":440100,"birthday":0,"userId":38352389,"userType":0,"nickname":"面包碎碎念","signature":"温柔而坚定，孤独而自由","description":"","detailDescription":"","avatarImgId":6671836558105156,"backgroundImgId":109951163780862940,"backgroundUrl":"http://p1.music.126.net/jUA0EG9n3jlbAWMgGs5eCg==/109951163780862940.jpg","authority":0,"mutual":false,"expertTags":null,"experts":null,"djStatus":0,"vipType":11,"remarkName":null,"authenticationTypes":0,"avatarDetail":null,"anchor":false,"avatarImgIdStr":"6671836558105156","backgroundImgIdStr":"109951163780862940"},{"defaultAvatar":false,"province":1000000,"authStatus":0,"followed":false,"avatarUrl":"http://p1.music.126.net/QaCW87YVZey9oo-1lhwLoQ==/18779658604583833.jpg","accountStatus":0,"gender":1,"city":1005700,"birthday":0,"userId":616618652,"userType":310,"nickname":"盛夏--剩下","signature":"只有音乐才是我的解药","description":"","detailDescription":"","avatarImgId":18779658604583830,"backgroundImgId":109951164720565200,"backgroundUrl":"http://p1.music.126.net/rOsAhbU7307OD1PDdEdNDQ==/109951164720565197.jpg","authority":0,"mutual":false,"expertTags":null,"experts":null,"djStatus":0,"vipType":11,"remarkName":null,"authenticationTypes":1048576,"avatarDetail":{"userType":310,"identityLevel":1,"identityIconUrl":"https://p6.music.126.net/obj/wonDlsKUwrLClGjCm8Kx/11231824940/04ea/70e2/d8d6/c6266e898b0c546a477e978c1bd9fdb2.png"},"anchor":false,"avatarImgIdStr":"18779658604583833","backgroundImgIdStr":"109951164720565197","avatarImgId_str":"18779658604583833"},{"defaultAvatar":false,"province":530000,"authStatus":0,"followed":false,"avatarUrl":"http://p1.music.126.net/i49QHeLCAdc8pR125cddxA==/109951168277845357.jpg","accountStatus":0,"gender":2,"city":530100,"birthday":0,"userId":1528570202,"userType":0,"nickname":"oldsoup-","signature":"","description":"","detailDescription":"","avatarImgId":109951168277845360,"backgroundImgId":109951165503662240,"backgroundUrl":"http://p1.music.126.net/rF_7JrqKsTSG8uCsljerIQ==/109951165503662233.jpg","authority":0,"mutual":false,"expertTags":null,"experts":null,"djStatus":0,"vipType":11,"remarkName":null,"authenticationTypes":0,"avatarDetail":null,"anchor":false,"avatarImgIdStr":"109951168277845357","backgroundImgIdStr":"109951165503662233","avatarImgId_str":"109951168277845357"},{"defaultAvatar":false,"province":340000,"authStatus":0,"followed":false,"avatarUrl":"http://p1.music.126.net/Usbd9XAs5rRUWuaZ7KiK6A==/18662010860143269.jpg","accountStatus":0,"gender":1,"city":340100,"birthday":0,"userId":539474416,"userType":0,"nickname":"Backagain-","signature":"Oh take me back to the start。","description":"","detailDescription":"","avatarImgId":18662010860143268,"backgroundImgId":109951162868128400,"backgroundUrl":"http://p1.music.126.net/2zSNIqTcpHL2jIvU6hG0EA==/109951162868128395.jpg","authority":0,"mutual":false,"expertTags":null,"experts":null,"djStatus":0,"vipType":11,"remarkName":null,"authenticationTypes":0,"avatarDetail":null,"anchor":false,"avatarImgIdStr":"18662010860143269","backgroundImgIdStr":"109951162868128395","avatarImgId_str":"18662010860143269"},{"defaultAvatar":false,"province":610000,"authStatus":0,"followed":false,"avatarUrl":"http://p1.music.126.net/hpASX8dy6_k2dsG1F_Fuew==/109951163767940232.jpg","accountStatus":0,"gender":1,"city":610100,"birthday":0,"userId":90348498,"userType":0,"nickname":"傅果果他爹","signature":"","description":"","detailDescription":"","avatarImgId":109951163767940220,"backgroundImgId":2002210674180202,"backgroundUrl":"http://p1.music.126.net/pmHS4fcQtcNEGewNb5HRhg==/2002210674180202.jpg","authority":0,"mutual":false,"expertTags":null,"experts":null,"djStatus":0,"vipType":0,"remarkName":null,"authenticationTypes":0,"avatarDetail":null,"anchor":false,"avatarImgIdStr":"109951163767940232","backgroundImgIdStr":"2002210674180202","avatarImgId_str":"109951163767940232"},{"defaultAvatar":false,"province":230000,"authStatus":0,"followed":false,"avatarUrl":"http://p1.music.126.net/ljnSwA99K3idbLxT35O9gg==/109951165974133758.jpg","accountStatus":0,"gender":1,"city":230100,"birthday":0,"userId":110687265,"userType":0,"nickname":"在聆听吗","signature":"大象没有眼泪，可他却想要流泪","description":"","detailDescription":"","avatarImgId":109951165974133760,"backgroundImgId":109951165456573950,"backgroundUrl":"http://p1.music.126.net/oHNJ-lHiX1zwj-eDGqt7Vg==/109951165456573954.jpg","authority":0,"mutual":false,"expertTags":null,"experts":null,"djStatus":0,"vipType":11,"remarkName":null,"authenticationTypes":0,"avatarDetail":null,"anchor":false,"avatarImgIdStr":"109951165974133758","backgroundImgIdStr":"109951165456573954","avatarImgId_str":"109951165974133758"},{"defaultAvatar":false,"province":1000000,"authStatus":0,"followed":false,"avatarUrl":"http://p1.music.126.net/L8oV6RILZpUhm1XFtKQ5vQ==/109951163141347108.jpg","accountStatus":0,"gender":0,"city":1004900,"birthday":0,"userId":574000875,"userType":0,"nickname":"林羡鱼小姐","signature":"喜欢各种好听的声音。","description":"","detailDescription":"","avatarImgId":109951163141347100,"backgroundImgId":109951163098746080,"backgroundUrl":"http://p1.music.126.net/RuJBcHEgH7SmJGkKVpRvtg==/109951163098746078.jpg","authority":0,"mutual":false,"expertTags":null,"experts":null,"djStatus":0,"vipType":11,"remarkName":null,"authenticationTypes":0,"avatarDetail":null,"anchor":false,"avatarImgIdStr":"109951163141347108","backgroundImgIdStr":"109951163098746078","avatarImgId_str":"109951163141347108"},{"defaultAvatar":false,"province":440000,"authStatus":0,"followed":false,"avatarUrl":"http://p1.music.126.net/q7jWZnk-dvj9dLHGdalpCw==/109951168505097797.jpg","accountStatus":0,"gender":2,"city":440100,"birthday":0,"userId":275076142,"userType":0,"nickname":"-_-Menimar","signature":"愿漂泊的人都有酒喝，愿你最爱的人也最爱你。","description":"","detailDescription":"","avatarImgId":109951168505097800,"backgroundImgId":109951163343721820,"backgroundUrl":"http://p1.music.126.net/07sNWyfPq8PbwlEwbtzb9g==/109951163343721818.jpg","authority":0,"mutual":false,"expertTags":null,"experts":null,"djStatus":0,"vipType":11,"remarkName":null,"authenticationTypes":0,"avatarDetail":null,"anchor":false,"avatarImgIdStr":"109951168505097797","backgroundImgIdStr":"109951163343721818","avatarImgId_str":"109951168505097797"}],"subscribed":false,"creator":{"defaultAvatar":false,"province":310000,"authStatus":0,"followed":false,"avatarUrl":"http://p1.music.126.net/dRf7W7t0MB6bzfYGjskwoA==/6017627139384597.jpg","accountStatus":0,"gender":1,"city":310101,"birthday":0,"userId":20226098,"userType":0,"nickname":"大藏藏","signature":"oh my international cool playboy!","description":"","detailDescription":"","avatarImgId":6017627139384597,"backgroundImgId":109951166202689170,"backgroundUrl":"http://p1.music.126.net/lt1K0huJagqDwbrmkUcYPA==/109951166202689168.jpg","authority":0,"mutual":false,"expertTags":null,"experts":null,"djStatus":0,"vipType":11,"remarkName":null,"authenticationTypes":0,"avatarDetail":null,"anchor":false,"avatarImgIdStr":"6017627139384597","backgroundImgIdStr":"109951166202689168"},"tracks":[{"name":"燃烧的爱情 feat.李鹏(反光镜)","id":1319891450,"pst":0,"t":0,"ar":[{"id":13056,"name":"闪星TwinkleStar","tns":[],"alias":[]}],"alia":[],"pop":70,"st":0,"rt":"","fee":8,"v":28,"crbt":null,"cf":"","al":{"id":74355954,"name":"《星火 TWINKLE IN THE DARK》","picUrl":"http://p2.music.126.net/Uz9XkA1gKxQJa7bnouULRw==/109951163661848704.jpg","tns":[],"pic_str":"109951163661848704","pic":109951163661848700},"dt":281419,"h":{"br":320000,"fid":0,"size":11259864,"vd":-66543,"sr":44100},"m":{"br":192000,"fid":0,"size":6755936,"vd":-64006,"sr":44100},"l":{"br":128000,"fid":0,"size":4503972,"vd":-62557,"sr":44100},"sq":{"br":1020259,"fid":0,"size":35890172,"vd":-66536,"sr":44100},"hr":null,"a":null,"cd":"01","no":4,"rtUrl":null,"ftype":0,"rtUrls":[],"djId":0,"copyright":2,"s_id":0,"mark":8192,"originCoverType":0,"originSongSimpleData":null,"tagPicList":null,"resourceState":true,"version":28,"songJumpInfo":null,"entertainmentTags":null,"awardTags":null,"single":0,"noCopyrightRcmd":null,"mst":9,"cp":0,"mv":10891936,"rtype":0,"rurl":null,"publishTime":1540279243096},{"name":"亲爱的","id":1920622020,"pst":0,"t":0,"ar":[{"id":10875,"name":"郑宜农","tns":[],"alias":[]}],"alia":[],"pop":70,"st":0,"rt":"","fee":8,"v":7,"crbt":null,"cf":"","al":{"id":140436738,"name":"水逆","picUrl":"http://p1.music.126.net/2_bfGl0Z9m91WIrJnH4WSQ==/109951167054111857.jpg","tns":[],"pic_str":"109951167054111857","pic":109951167054111860},"dt":245826,"h":{"br":320000,"fid":0,"size":9835668,"vd":-35412,"sr":44100},"m":{"br":192000,"fid":0,"size":5901418,"vd":-32786,"sr":44100},"l":{"br":128000,"fid":0,"size":3934293,"vd":-31060,"sr":44100},"sq":{"br":922840,"fid":0,"size":28357365,"vd":-35049,"sr":44100},"hr":null,"a":null,"cd":"01","no":5,"rtUrl":null,"ftype":0,"rtUrls":[],"djId":0,"copyright":1,"s_id":0,"mark":8192,"originCoverType":0,"originSongSimpleData":null,"tagPicList":null,"resourceState":true,"version":7,"songJumpInfo":null,"entertainmentTags":null,"awardTags":null,"single":0,"noCopyrightRcmd":null,"mst":9,"cp":1416336,"mv":0,"rtype":0,"rurl":null,"publishTime":1646323200000},{"name":"Darling","id":1378905811,"pst":0,"t":0,"ar":[{"id":32797504,"name":"爱是唯一","tns":[],"alias":[]}],"alia":[],"pop":75,"st":0,"rt":"","fee":8,"v":9,"crbt":null,"cf":"","al":{"id":80498291,"name":"爱是唯一","picUrl":"http://p1.music.126.net/KR4ygYh_wVM1fD1xP1EL7A==/109951164224317153.jpg","tns":[],"pic_str":"109951164224317153","pic":109951164224317150},"dt":462500,"h":{"br":320000,"fid":0,"size":18502209,"vd":-43594,"sr":48000},"m":{"br":192000,"fid":0,"size":11101377,"vd":-41031,"sr":48000},"l":{"br":128000,"fid":0,"size":7400961,"vd":-39408,"sr":48000},"sq":{"br":859082,"fid":0,"size":49665712,"vd":-43713,"sr":48000},"hr":{"br":1622273,"fid":0,"size":93787674,"vd":-43649,"sr":48000},"a":null,"cd":"01","no":5,"rtUrl":null,"ftype":0,"rtUrls":[],"djId":0,"copyright":1,"s_id":0,"mark":536879104,"originCoverType":0,"originSongSimpleData":null,"tagPicList":null,"resourceState":true,"version":9,"songJumpInfo":null,"entertainmentTags":null,"awardTags":null,"single":0,"noCopyrightRcmd":null,"mst":9,"cp":1400821,"mv":0,"rtype":0,"rurl":null,"publishTime":1563552000000},{"name":"决定性瞬间","id":1982989197,"pst":0,"t":0,"ar":[{"id":12318046,"name":"愚月FoolMoon","tns":[],"alias":[]},{"id":12029112,"name":"椅子乐团 The Chairs","tns":[],"alias":[]}],"alia":[],"pop":95,"st":0,"rt":"","fee":8,"v":5,"crbt":null,"cf":"","al":{"id":151902800,"name":"决定性瞬间","picUrl":"http://p1.music.126.net/_-LKfWYJmvLJChZQEH5eeg==/109951167893884489.jpg","tns":["Decisive Moment"],"pic_str":"109951167893884489","pic":109951167893884500},"dt":252000,"h":{"br":320001,"fid":0,"size":10081965,"vd":-40742,"sr":48000},"m":{"br":192001,"fid":0,"size":6049197,"vd":-38135,"sr":48000},"l":{"br":128001,"fid":0,"size":4032813,"vd":-36404,"sr":48000},"sq":{"br":942058,"fid":0,"size":29674845,"vd":-40736,"sr":48000},"hr":{"br":1711596,"fid":0,"size":53915291,"vd":-40736,"sr":48000},"a":null,"cd":"01","no":3,"rtUrl":null,"ftype":0,"rtUrls":[],"djId":0,"copyright":0,"s_id":0,"mark":536879104,"originCoverType":0,"originSongSimpleData":null,"tagPicList":null,"resourceState":true,"version":5,"songJumpInfo":null,"entertainmentTags":null,"awardTags":null,"single":0,"noCopyrightRcmd":null,"mst":9,"cp":0,"mv":0,"rtype":0,"rurl":null,"publishTime":0,"tns":["Decisive Moment"]},{"name":"城市潛水","id":1390389051,"pst":0,"t":0,"ar":[{"id":12029112,"name":"椅子乐团 The Chairs","tns":[],"alias":[]}],"alia":[],"pop":95,"st":0,"rt":"","fee":8,"v":23,"crbt":null,"cf":"","al":{"id":81578314,"name":"城市潛水","picUrl":"http://p1.music.126.net/K3C44wT3qM5z6ZQ56lLeLQ==/109951164418148586.jpg","tns":[],"pic_str":"109951164418148586","pic":109951164418148590},"dt":211149,"h":{"br":320000,"fid":0,"size":8449089,"vd":-46089,"sr":44100},"m":{"br":192000,"fid":0,"size":5069471,"vd":-43496,"sr":44100},"l":{"br":128000,"fid":0,"size":3379662,"vd":-41838,"sr":44100},"sq":{"br":1103000,"fid":0,"size":23256613,"vd":-46083,"sr":44100},"hr":null,"a":null,"cd":"01","no":1,"rtUrl":null,"ftype":0,"rtUrls":[],"djId":0,"copyright":1,"s_id":0,"mark":270336,"originCoverType":0,"originSongSimpleData":null,"tagPicList":null,"resourceState":true,"version":23,"songJumpInfo":null,"entertainmentTags":null,"awardTags":null,"single":0,"noCopyrightRcmd":null,"mst":9,"cp":405025,"mv":10943360,"rtype":0,"rurl":null,"publishTime":1569340800000},{"name":"黑洞里","id":82187,"pst":0,"t":0,"ar":[{"id":2738,"name":"方大同","tns":[],"alias":[]}],"alia":[],"pop":100,"st":0,"rt":"600902000006266897","fee":1,"v":25,"crbt":null,"cf":"","al":{"id":8116,"name":"橙月 Orange Moon","picUrl":"http://p1.music.126.net/5P_17lGBcqlrcXYs1gF26w==/109951168306753554.jpg","tns":[],"pic_str":"109951168306753554","pic":109951168306753550},"dt":213586,"h":{"br":320000,"fid":0,"size":8546264,"vd":-19396,"sr":44100},"m":{"br":192000,"fid":0,"size":5127776,"vd":-16836,"sr":44100},"l":{"br":128000,"fid":0,"size":3418532,"vd":-15179,"sr":44100},"sq":{"br":887729,"fid":0,"size":23700903,"vd":-21191,"sr":44100},"hr":null,"a":null,"cd":"1","no":6,"rtUrl":null,"ftype":0,"rtUrls":[],"djId":0,"copyright":1,"s_id":0,"mark":8192,"originCoverType":1,"originSongSimpleData":null,"tagPicList":null,"resourceState":true,"version":25,"songJumpInfo":null,"entertainmentTags":null,"awardTags":null,"single":0,"noCopyrightRcmd":null,"mst":9,"cp":7002,"mv":0,"rtype":0,"rurl":null,"publishTime":1230307200000},{"name":"小狗落回你身旁","id":1975270702,"pst":0,"t":0,"ar":[{"id":12118540,"name":"动物园钉子户","tns":[],"alias":[]}],"alia":[],"pop":95,"st":0,"rt":"","fee":8,"v":4,"crbt":null,"cf":"","al":{"id":150295927,"name":"小狗落回你身旁","picUrl":"http://p2.music.126.net/0XUhPU5sgZeT2xA2_zp1sg==/109951167815086000.jpg","tns":[],"pic_str":"109951167815086000","pic":109951167815086000},"dt":254814,"h":{"br":320000,"fid":0,"size":10195113,"vd":-10378,"sr":44100},"m":{"br":192000,"fid":0,"size":6117085,"vd":-7761,"sr":44100},"l":{"br":128000,"fid":0,"size":4078071,"vd":-6057,"sr":44100},"sq":{"br":1516377,"fid":0,"size":48299421,"vd":-10374,"sr":44100},"hr":null,"a":null,"cd":"01","no":1,"rtUrl":null,"ftype":0,"rtUrls":[],"djId":0,"copyright":0,"s_id":0,"mark":8192,"originCoverType":0,"originSongSimpleData":null,"tagPicList":null,"resourceState":true,"version":4,"songJumpInfo":null,"entertainmentTags":null,"awardTags":null,"single":0,"noCopyrightRcmd":null,"mst":9,"cp":0,"mv":0,"rtype":0,"rurl":null,"publishTime":0},{"name":"靛蓝","id":1432514639,"pst":0,"t":0,"ar":[{"id":13195351,"name":"荷尔蒙少年 Hormone Boys","tns":[],"alias":[]}],"alia":[],"pop":25,"st":0,"rt":"","fee":8,"v":9,"crbt":null,"cf":"","al":{"id":86683857,"name":"黑色台北","picUrl":"http://p1.music.126.net/Wb1LISQNYO-k1Q7h15-FcQ==/109951164821405645.jpg","tns":[],"pic_str":"109951164821405645","pic":109951164821405650},"dt":317506,"h":{"br":320000,"fid":0,"size":12702868,"vd":-55311,"sr":44100},"m":{"br":192000,"fid":0,"size":7621738,"vd":-52770,"sr":44100},"l":{"br":128000,"fid":0,"size":5081173,"vd":-51433,"sr":44100},"sq":{"br":1411000,"fid":0,"size":36150671,"vd":-55306,"sr":44100},"hr":null,"a":null,"cd":"01","no":5,"rtUrl":null,"ftype":0,"rtUrls":[],"djId":0,"copyright":1,"s_id":0,"mark":270336,"originCoverType":0,"originSongSimpleData":null,"tagPicList":null,"resourceState":true,"version":9,"songJumpInfo":null,"entertainmentTags":null,"awardTags":null,"single":0,"noCopyrightRcmd":null,"mst":9,"cp":1400821,"mv":0,"rtype":0,"rurl":null,"publishTime":1586361600000},{"name":"贰拾","id":1369404553,"pst":0,"t":0,"ar":[{"id":13195351,"name":"荷尔蒙少年 Hormone Boys","tns":[],"alias":[]}],"alia":[],"pop":25,"st":0,"rt":"","fee":8,"v":14,"crbt":null,"cf":"","al":{"id":79572967,"name":"贰拾","picUrl":"http://p1.music.126.net/flgBYbWxIHMkmA-M66_zEw==/109951164119857738.jpg","tns":[],"pic_str":"109951164119857738","pic":109951164119857740},"dt":286045,"h":{"br":320001,"fid":0,"size":11444289,"vd":-44634,"sr":48000},"m":{"br":192001,"fid":0,"size":6866625,"vd":-42061,"sr":48000},"l":{"br":128001,"fid":0,"size":4577793,"vd":-40438,"sr":48000},"sq":{"br":985491,"fid":0,"size":35236922,"vd":-44655,"sr":48000},"hr":{"br":1753508,"fid":0,"size":62697876,"vd":-44626,"sr":48000},"a":null,"cd":"01","no":1,"rtUrl":null,"ftype":0,"rtUrls":[],"djId":0,"copyright":1,"s_id":0,"mark":537141248,"originCoverType":0,"originSongSimpleData":null,"tagPicList":null,"resourceState":true,"version":14,"songJumpInfo":null,"entertainmentTags":null,"awardTags":null,"single":0,"noCopyrightRcmd":null,"mst":9,"cp":1400821,"mv":0,"rtype":0,"rurl":null,"publishTime":1561910400000},{"name":"脸","id":299904,"pst":0,"t":0,"ar":[{"id":9621,"name":"王菲","tns":[],"alias":[]}],"alia":[],"pop":95,"st":0,"rt":"600902000009069799","fee":1,"v":80,"crbt":null,"cf":"","al":{"id":29725,"name":"唱游","picUrl":"http://p1.music.126.net/GNzeJIFvWVCn5bXQf8FHqg==/109951166214531766.jpg","tns":[],"pic_str":"109951166214531766","pic":109951166214531760},"dt":214400,"h":{"br":320000,"fid":0,"size":8578656,"vd":-23551,"sr":44100},"m":{"br":192000,"fid":0,"size":5147211,"vd":-23551,"sr":44100},"l":{"br":128000,"fid":0,"size":3431488,"vd":-23551,"sr":44100},"sq":{"br":885568,"fid":0,"size":23733225,"vd":-23551,"sr":44100},"hr":null,"a":null,"cd":"1","no":2,"rtUrl":null,"ftype":0,"rtUrls":[],"djId":0,"copyright":2,"s_id":518018855,"mark":8192,"originCoverType":1,"originSongSimpleData":null,"tagPicList":null,"resourceState":true,"version":79,"songJumpInfo":null,"entertainmentTags":null,"awardTags":null,"single":0,"noCopyrightRcmd":null,"mst":9,"cp":600011,"mv":284192,"rtype":0,"rurl":null,"publishTime":907257600007,"pc":{"nickname":"","alb":"唱游","fn":"02 - 脸.mp3","cid":"109951164199876776","br":326,"uid":20226098,"ar":"王菲","version":1,"sn":"脸"}}],"videoIds":null,"videos":null,"trackIds":[{"id":1319891450,"v":29,"t":0,"at":1686063338546,"alg":null,"uid":334095530,"rcmdReason":"","sc":null,"f":null,"sr":null},{"id":1920622020,"v":8,"t":0,"at":1686063334910,"alg":null,"uid":334095530,"rcmdReason":"","sc":null,"f":null,"sr":null},{"id":1378905811,"v":10,"t":0,"at":1686063330707,"alg":null,"uid":334095530,"rcmdReason":"","sc":null,"f":null,"sr":null},{"id":1982989197,"v":6,"t":0,"at":1686059384865,"alg":null,"uid":135858701,"rcmdReason":"","sc":null,"f":null,"sr":null},{"id":1390389051,"v":24,"t":0,"at":1686059293222,"alg":null,"uid":321118040,"rcmdReason":"","sc":null,"f":null,"sr":null},{"id":82187,"v":26,"t":0,"at":1686059222070,"alg":null,"uid":135858701,"rcmdReason":"","sc":null,"f":null,"sr":null},{"id":1975270702,"v":5,"t":0,"at":1686059180673,"alg":null,"uid":321118040,"rcmdReason":"","sc":null,"f":null,"sr":null},{"id":1432514639,"v":10,"t":0,"at":1686059170744,"alg":null,"uid":321118040,"rcmdReason":"","sc":null,"f":null,"sr":null},{"id":1369404553,"v":15,"t":0,"at":1686059155422,"alg":null,"uid":135858701,"rcmdReason":"","sc":null,"f":null,"sr":null},{"id":299904,"v":80,"t":0,"at":1686059101075,"alg":null,"uid":296658058,"rcmdReason":"","sc":null,"f":null,"sr":null}],"bannedTrackIds":null,"mvResourceInfos":null,"shareCount":7,"commentCount":196,"remixVideo":null,"sharedUsers":[{"defaultAvatar":false,"province":110000,"authStatus":0,"followed":false,"avatarUrl":"http://p1.music.126.net/YiCVHfj_d1iOtIz_RUYEsg==/109951165423851551.jpg","accountStatus":0,"gender":2,"city":110107,"birthday":0,"userId":296658058,"userType":0,"nickname":"吼吼破喉咙","signature":"一面笑的天真无邪，一面看破一切……","description":"","detailDescription":"","avatarImgId":109951165423851550,"backgroundImgId":2002210674180202,"backgroundUrl":"http://p1.music.126.net/pmHS4fcQtcNEGewNb5HRhg==/2002210674180202.jpg","authority":0,"mutual":false,"expertTags":null,"experts":null,"djStatus":0,"vipType":11,"remarkName":null,"authenticationTypes":0,"avatarDetail":null,"anchor":false,"avatarImgIdStr":"109951165423851551","backgroundImgIdStr":"2002210674180202","avatarImgId_str":"109951165423851551"},{"defaultAvatar":false,"province":110000,"authStatus":0,"followed":false,"avatarUrl":"http://p1.music.126.net/peLYNbyKDihfxMshtEsXfw==/109951165692417947.jpg","accountStatus":0,"gender":1,"city":110101,"birthday":0,"userId":135858701,"userType":0,"nickname":"橙月leo","signature":"你应该知道","description":"","detailDescription":"","avatarImgId":109951165692417950,"backgroundImgId":18567452860314790,"backgroundUrl":"http://p1.music.126.net/ERjG9gA4EeXFU_fxjj-lDw==/18567452860314791.jpg","authority":0,"mutual":false,"expertTags":null,"experts":null,"djStatus":0,"vipType":11,"remarkName":null,"authenticationTypes":4096,"avatarDetail":null,"anchor":true,"avatarImgIdStr":"109951165692417947","backgroundImgIdStr":"18567452860314791","avatarImgId_str":"109951165692417947"},{"defaultAvatar":false,"province":440000,"authStatus":0,"followed":false,"avatarUrl":"http://p1.music.126.net/EKC5Hg0KgDLQircPLAKzoA==/109951166161966162.jpg","accountStatus":0,"gender":0,"city":440100,"birthday":0,"userId":321118040,"userType":0,"nickname":"EMILYwhatever","signature":"","description":"","detailDescription":"","avatarImgId":109951166161966160,"backgroundImgId":109951164121604780,"backgroundUrl":"http://p1.music.126.net/OG4l7s7LR7enETTy4a88vA==/109951164121604785.jpg","authority":0,"mutual":false,"expertTags":null,"experts":null,"djStatus":0,"vipType":11,"remarkName":null,"authenticationTypes":0,"avatarDetail":null,"anchor":false,"avatarImgIdStr":"109951166161966162","backgroundImgIdStr":"109951164121604785","avatarImgId_str":"109951166161966162"},{"defaultAvatar":false,"province":440000,"authStatus":0,"followed":false,"avatarUrl":"http://p1.music.126.net/RdmWmBP8amYD7q2P0pJy3w==/109951166302119763.jpg","accountStatus":0,"gender":1,"city":440100,"birthday":0,"userId":334095530,"userType":0,"nickname":"啃啃坑坑","signature":"","description":"","detailDescription":"","avatarImgId":109951166302119760,"backgroundImgId":109951166302133100,"backgroundUrl":"http://p1.music.126.net/aCjLbTGRioSk9MIwLuYlwg==/109951166302133107.jpg","authority":0,"mutual":false,"expertTags":null,"experts":null,"djStatus":0,"vipType":11,"remarkName":null,"authenticationTypes":0,"avatarDetail":null,"anchor":false,"avatarImgIdStr":"109951166302119763","backgroundImgIdStr":"109951166302133107","avatarImgId_str":"109951166302119763"}],"historySharedUsers":[],"gradeStatus":"NONE","score":null,"algTags":null},"urls":null,"privileges":[{"id":1319891450,"fee":8,"payed":1,"realPayed":0,"st":0,"pl":999000,"dl":999000,"sp":7,"cp":1,"subp":1,"cs":false,"maxbr":999000,"fl":128000,"pc":null,"toast":false,"flag":4,"paidBigBang":false,"preSell":false,"playMaxbr":999000,"downloadMaxbr":999000,"maxBrLevel":"lossless","playMaxBrLevel":"lossless","downloadMaxBrLevel":"lossless","plLevel":"lossless","dlLevel":"lossless","flLevel":"standard","rscl":null,"freeTrialPrivilege":{"resConsumable":false,"userConsumable":false,"listenType":null,"cannotListenReason":null},"rightSource":0,"chargeInfoList":[{"rate":128000,"chargeUrl":null,"chargeMessage":null,"chargeType":0},{"rate":192000,"chargeUrl":null,"chargeMessage":null,"chargeType":1},{"rate":320000,"chargeUrl":null,"chargeMessage":null,"chargeType":1},{"rate":999000,"chargeUrl":null,"chargeMessage":null,"chargeType":1}]},{"id":1920622020,"fee":8,"payed":1,"realPayed":0,"st":0,"pl":999000,"dl":999000,"sp":7,"cp":1,"subp":1,"cs":false,"maxbr":999000,"fl":128000,"pc":null,"toast":false,"flag":4,"paidBigBang":false,"preSell":false,"playMaxbr":999000,"downloadMaxbr":999000,"maxBrLevel":"lossless","playMaxBrLevel":"lossless","downloadMaxBrLevel":"lossless","plLevel":"lossless","dlLevel":"lossless","flLevel":"standard","rscl":null,"freeTrialPrivilege":{"resConsumable":false,"userConsumable":false,"listenType":null,"cannotListenReason":null},"rightSource":0,"chargeInfoList":[{"rate":128000,"chargeUrl":null,"chargeMessage":null,"chargeType":0},{"rate":192000,"chargeUrl":null,"chargeMessage":null,"chargeType":1},{"rate":320000,"chargeUrl":null,"chargeMessage":null,"chargeType":1},{"rate":999000,"chargeUrl":null,"chargeMessage":null,"chargeType":1}]},{"id":1378905811,"fee":8,"payed":1,"realPayed":0,"st":0,"pl":999000,"dl":999000,"sp":7,"cp":1,"subp":1,"cs":false,"maxbr":999000,"fl":128000,"pc":null,"toast":false,"flag":260,"paidBigBang":false,"preSell":false,"playMaxbr":999000,"downloadMaxbr":999000,"maxBrLevel":"hires","playMaxBrLevel":"hires","downloadMaxBrLevel":"hires","plLevel":"hires","dlLevel":"hires","flLevel":"standard","rscl":null,"freeTrialPrivilege":{"resConsumable":false,"userConsumable":false,"listenType":null,"cannotListenReason":null},"rightSource":0,"chargeInfoList":[{"rate":128000,"chargeUrl":null,"chargeMessage":null,"chargeType":0},{"rate":192000,"chargeUrl":null,"chargeMessage":null,"chargeType":1},{"rate":320000,"chargeUrl":null,"chargeMessage":null,"chargeType":1},{"rate":999000,"chargeUrl":null,"chargeMessage":null,"chargeType":1},{"rate":1999000,"chargeUrl":null,"chargeMessage":null,"chargeType":1}]},{"id":1982989197,"fee":8,"payed":1,"realPayed":0,"st":0,"pl":999000,"dl":999000,"sp":7,"cp":1,"subp":1,"cs":false,"maxbr":999000,"fl":128000,"pc":null,"toast":false,"flag":4,"paidBigBang":false,"preSell":false,"playMaxbr":999000,"downloadMaxbr":999000,"maxBrLevel":"hires","playMaxBrLevel":"hires","downloadMaxBrLevel":"hires","plLevel":"hires","dlLevel":"hires","flLevel":"standard","rscl":null,"freeTrialPrivilege":{"resConsumable":false,"userConsumable":false,"listenType":null,"cannotListenReason":null},"rightSource":0,"chargeInfoList":[{"rate":128000,"chargeUrl":null,"chargeMessage":null,"chargeType":0},{"rate":192000,"chargeUrl":null,"chargeMessage":null,"chargeType":1},{"rate":320000,"chargeUrl":null,"chargeMessage":null,"chargeType":1},{"rate":999000,"chargeUrl":null,"chargeMessage":null,"chargeType":1},{"rate":1999000,"chargeUrl":null,"chargeMessage":null,"chargeType":1}]},{"id":1390389051,"fee":8,"payed":1,"realPayed":0,"st":0,"pl":999000,"dl":999000,"sp":7,"cp":1,"subp":1,"cs":false,"maxbr":999000,"fl":128000,"pc":null,"toast":false,"flag":4,"paidBigBang":false,"preSell":false,"playMaxbr":999000,"downloadMaxbr":999000,"maxBrLevel":"lossless","playMaxBrLevel":"lossless","downloadMaxBrLevel":"lossless","plLevel":"lossless","dlLevel":"lossless","flLevel":"standard","rscl":null,"freeTrialPrivilege":{"resConsumable":false,"userConsumable":false,"listenType":null,"cannotListenReason":null},"rightSource":0,"chargeInfoList":[{"rate":128000,"chargeUrl":null,"chargeMessage":null,"chargeType":0},{"rate":192000,"chargeUrl":null,"chargeMessage":null,"chargeType":1},{"rate":320000,"chargeUrl":null,"chargeMessage":null,"chargeType":1},{"rate":999000,"chargeUrl":null,"chargeMessage":null,"chargeType":1}]},{"id":82187,"fee":1,"payed":1,"realPayed":0,"st":0,"pl":999000,"dl":999000,"sp":7,"cp":1,"subp":1,"cs":false,"maxbr":999000,"fl":0,"pc":null,"toast":false,"flag":260,"paidBigBang":false,"preSell":false,"playMaxbr":999000,"downloadMaxbr":999000,"maxBrLevel":"lossless","playMaxBrLevel":"lossless","downloadMaxBrLevel":"lossless","plLevel":"lossless","dlLevel":"lossless","flLevel":"none","rscl":null,"freeTrialPrivilege":{"resConsumable":false,"userConsumable":false,"listenType":null,"cannotListenReason":null},"rightSource":0,"chargeInfoList":[{"rate":128000,"chargeUrl":null,"chargeMessage":null,"chargeType":1},{"rate":192000,"chargeUrl":null,"chargeMessage":null,"chargeType":1},{"rate":320000,"chargeUrl":null,"chargeMessage":null,"chargeType":1},{"rate":999000,"chargeUrl":null,"chargeMessage":null,"chargeType":1}]},{"id":1975270702,"fee":8,"payed":1,"realPayed":0,"st":0,"pl":999000,"dl":999000,"sp":7,"cp":1,"subp":1,"cs":false,"maxbr":999000,"fl":128000,"pc":null,"toast":false,"flag":4,"paidBigBang":false,"preSell":false,"playMaxbr":999000,"downloadMaxbr":999000,"maxBrLevel":"lossless","playMaxBrLevel":"lossless","downloadMaxBrLevel":"lossless","plLevel":"lossless","dlLevel":"lossless","flLevel":"standard","rscl":null,"freeTrialPrivilege":{"resConsumable":false,"userConsumable":false,"listenType":null,"cannotListenReason":null},"rightSource":0,"chargeInfoList":[{"rate":128000,"chargeUrl":null,"chargeMessage":null,"chargeType":0},{"rate":192000,"chargeUrl":null,"chargeMessage":null,"chargeType":1},{"rate":320000,"chargeUrl":null,"chargeMessage":null,"chargeType":1},{"rate":999000,"chargeUrl":null,"chargeMessage":null,"chargeType":1}]},{"id":1432514639,"fee":8,"payed":1,"realPayed":0,"st":0,"pl":999000,"dl":999000,"sp":7,"cp":1,"subp":1,"cs":false,"maxbr":999000,"fl":128000,"pc":null,"toast":false,"flag":260,"paidBigBang":false,"preSell":false,"playMaxbr":999000,"downloadMaxbr":999000,"maxBrLevel":"lossless","playMaxBrLevel":"lossless","downloadMaxBrLevel":"lossless","plLevel":"lossless","dlLevel":"lossless","flLevel":"standard","rscl":null,"freeTrialPrivilege":{"resConsumable":false,"userConsumable":false,"listenType":null,"cannotListenReason":null},"rightSource":0,"chargeInfoList":[{"rate":128000,"chargeUrl":null,"chargeMessage":null,"chargeType":0},{"rate":192000,"chargeUrl":null,"chargeMessage":null,"chargeType":1},{"rate":320000,"chargeUrl":null,"chargeMessage":null,"chargeType":1},{"rate":999000,"chargeUrl":null,"chargeMessage":null,"chargeType":1}]},{"id":1369404553,"fee":8,"payed":1,"realPayed":0,"st":0,"pl":999000,"dl":999000,"sp":7,"cp":1,"subp":1,"cs":false,"maxbr":999000,"fl":128000,"pc":null,"toast":false,"flag":260,"paidBigBang":false,"preSell":false,"playMaxbr":999000,"downloadMaxbr":999000,"maxBrLevel":"hires","playMaxBrLevel":"hires","downloadMaxBrLevel":"hires","plLevel":"hires","dlLevel":"hires","flLevel":"standard","rscl":null,"freeTrialPrivilege":{"resConsumable":false,"userConsumable":false,"listenType":null,"cannotListenReason":null},"rightSource":0,"chargeInfoList":[{"rate":128000,"chargeUrl":null,"chargeMessage":null,"chargeType":0},{"rate":192000,"chargeUrl":null,"chargeMessage":null,"chargeType":1},{"rate":320000,"chargeUrl":null,"chargeMessage":null,"chargeType":1},{"rate":999000,"chargeUrl":null,"chargeMessage":null,"chargeType":1},{"rate":1999000,"chargeUrl":null,"chargeMessage":null,"chargeType":1}]},{"id":299904,"fee":1,"payed":1,"realPayed":0,"st":0,"pl":326000,"dl":326000,"sp":7,"cp":1,"subp":1,"cs":true,"maxbr":999000,"fl":0,"pc":{"id":289187829409,"userId":20226098,"songId":299904,"md5":"38b9e29df7aa84d12df7103f02524cef","song":"脸","artist":"王菲","album":"唱游","bitrate":326,"fileName":"02 - 脸.mp3","songDfsId":0,"cover":109951164199876770,"lyric":0,"cue":0,"convertLyric":0,"version":1,"addTime":1562516562217,"fileSize":8744701,"status":0,"originalAudioSongId":518018855,"lrcType":""},"toast":false,"flag":12,"paidBigBang":false,"preSell":false,"playMaxbr":999000,"downloadMaxbr":999000,"maxBrLevel":"lossless","playMaxBrLevel":"lossless","downloadMaxBrLevel":"lossless","plLevel":"exhigh","dlLevel":"exhigh","flLevel":"none","rscl":null,"freeTrialPrivilege":{"resConsumable":false,"userConsumable":false,"listenType":null,"cannotListenReason":null},"rightSource":0,"chargeInfoList":[{"rate":128000,"chargeUrl":null,"chargeMessage":null,"chargeType":1},{"rate":192000,"chargeUrl":null,"chargeMessage":null,"chargeType":1},{"rate":320000,"chargeUrl":null,"chargeMessage":null,"chargeType":1},{"rate":999000,"chargeUrl":null,"chargeMessage":null,"chargeType":1}]}],"sharedPrivilege":{"status":"SHARED","usePermission":"NORMAL"},"resEntrance":null,"fromUsers":null,"fromUserCount":0,"songFromUsers":null,"trialMode":11}