{"code":200,"relatedVideos":null,"playlist":{"id":6876152675,"name":"FM刘群音乐之声","coverImgId":109951166364914910,"coverImgUrl":"https://p1.music.126.net/TUihQh6D9cwKPe1S0mOKeA==/109951166364914915.jpg","coverImgId_str":"109951166364914915","adType":0,"userId":20226098,"createTime":1626964418634,"status":0,"opRecommend":false,"highQuality":false,"newImported":false,"updateTime":1690219429769,"trackCount":7,"specialType":300,"privacy":0,"trackUpdateTime":1690219429769,"commentThreadId":"A_PL_0_6876152675","playCount":6878,"trackNumberUpdateTime":1690219429769,"subscribedCount":82,"cloudTrackCount":0,"ordered":true,"description":"2023/07/25 主题：见面#薯薯","tags":["榜单"],"updateFrequency":null,"backgroundCoverId":0,"backgroundCoverUrl":null,"titleImage":0,"titleImageUrl":null,"englishTitle":null,"officialPlaylistType":null,"copied":false,"relateResType":null,"subscribers":[{"defaultAvatar":false,"province":370000,"authStatus":0,"followed":false,"avatarUrl":"http://p1.music.126.net/-9VLGNqUmQO0vQ6IPpa7ZQ==/109951168072289806.jpg","accountStatus":0,"gender":1,"city":370100,"birthday":0,"userId":1401759075,"userType":0,"nickname":"-Dysss","signature":"","description":"","detailDescription":"","avatarImgId":109951168072289810,"backgroundImgId":109951162868126480,"backgroundUrl":"http://p1.music.126.net/_f8R60U9mZ42sSNvdPn2sQ==/109951162868126486.jpg","authority":0,"mutual":false,"expertTags":null,"experts":null,"djStatus":0,"vipType":0,"remarkName":null,"authenticationTypes":0,"avatarDetail":null,"avatarImgIdStr":"109951168072289806","backgroundImgIdStr":"109951162868126486","anchor":false,"avatarImgId_str":"109951168072289806"},{"defaultAvatar":false,"province":370000,"authStatus":0,"followed":false,"avatarUrl":"http://p1.music.126.net/tuf2g-7EChjp_OAFM0AlkQ==/109951168537019278.jpg","accountStatus":0,"gender":1,"city":370500,"birthday":0,"userId":1483298661,"userType":0,"nickname":"滨尾矩考","signature":"","description":"","detailDescription":"","avatarImgId":109951168537019280,"backgroundImgId":109951162868126480,"backgroundUrl":"http://p1.music.126.net/_f8R60U9mZ42sSNvdPn2sQ==/109951162868126486.jpg","authority":0,"mutual":false,"expertTags":null,"experts":null,"djStatus":0,"vipType":11,"remarkName":null,"authenticationTypes":0,"avatarDetail":null,"avatarImgIdStr":"109951168537019278","backgroundImgIdStr":"109951162868126486","anchor":false,"avatarImgId_str":"109951168537019278"},{"defaultAvatar":false,"province":440000,"authStatus":0,"followed":false,"avatarUrl":"http://p1.music.126.net/ZgXig9k9tA0G9mS09IK7oQ==/6671836558105156.jpg","accountStatus":0,"gender":1,"city":440100,"birthday":0,"userId":38352389,"userType":0,"nickname":"面包碎碎念","signature":"温柔而坚定，孤独而自由","description":"","detailDescription":"","avatarImgId":6671836558105156,"backgroundImgId":109951163780862940,"backgroundUrl":"http://p1.music.126.net/jUA0EG9n3jlbAWMgGs5eCg==/109951163780862940.jpg","authority":0,"mutual":false,"expertTags":null,"experts":null,"djStatus":0,"vipType":11,"remarkName":null,"authenticationTypes":0,"avatarDetail":null,"avatarImgIdStr":"6671836558105156","backgroundImgIdStr":"109951163780862940","anchor":false},{"defaultAvatar":false,"province":1000000,"authStatus":0,"followed":false,"avatarUrl":"http://p1.music.126.net/QaCW87YVZey9oo-1lhwLoQ==/18779658604583833.jpg","accountStatus":0,"gender":1,"city":1005700,"birthday":0,"userId":616618652,"userType":310,"nickname":"盛夏--剩下","signature":"只有音乐才是我的解药","description":"","detailDescription":"","avatarImgId":18779658604583830,"backgroundImgId":109951164720565200,"backgroundUrl":"http://p1.music.126.net/rOsAhbU7307OD1PDdEdNDQ==/109951164720565197.jpg","authority":0,"mutual":false,"expertTags":null,"experts":null,"djStatus":0,"vipType":11,"remarkName":null,"authenticationTypes":1048576,"avatarDetail":{"userType":310,"identityLevel":2,"identityIconUrl":"https://p6.music.126.net/obj/wonDlsKUwrLClGjCm8Kx/11231827456/4f57/212d/6f78/c01bf6ac1b0228d8f365e13b6deea630.png"},"avatarImgIdStr":"18779658604583833","backgroundImgIdStr":"109951164720565197","anchor":false,"avatarImgId_str":"18779658604583833"},{"defaultAvatar":false,"province":430000,"authStatus":0,"followed":false,"avatarUrl":"http://p1.music.126.net/i49QHeLCAdc8pR125cddxA==/109951168277845357.jpg","accountStatus":0,"gender":2,"city":430600,"birthday":0,"userId":1528570202,"userType":0,"nickname":"oldsoup-","signature":"","description":"","detailDescription":"","avatarImgId":109951168277845360,"backgroundImgId":109951165503662240,"backgroundUrl":"http://p1.music.126.net/rF_7JrqKsTSG8uCsljerIQ==/109951165503662233.jpg","authority":0,"mutual":false,"expertTags":null,"experts":null,"djStatus":0,"vipType":11,"remarkName":null,"authenticationTypes":0,"avatarDetail":null,"avatarImgIdStr":"109951168277845357","backgroundImgIdStr":"109951165503662233","anchor":false,"avatarImgId_str":"109951168277845357"},{"defaultAvatar":false,"province":340000,"authStatus":0,"followed":false,"avatarUrl":"http://p1.music.126.net/Usbd9XAs5rRUWuaZ7KiK6A==/18662010860143269.jpg","accountStatus":0,"gender":1,"city":340100,"birthday":0,"userId":539474416,"userType":0,"nickname":"Backagain-","signature":"Oh take me back to the start。","description":"","detailDescription":"","avatarImgId":18662010860143268,"backgroundImgId":109951162868128400,"backgroundUrl":"http://p1.music.126.net/2zSNIqTcpHL2jIvU6hG0EA==/109951162868128395.jpg","authority":0,"mutual":false,"expertTags":null,"experts":null,"djStatus":0,"vipType":11,"remarkName":null,"authenticationTypes":0,"avatarDetail":null,"avatarImgIdStr":"18662010860143269","backgroundImgIdStr":"109951162868128395","anchor":false,"avatarImgId_str":"18662010860143269"},{"defaultAvatar":false,"province":230000,"authStatus":0,"followed":false,"avatarUrl":"http://p1.music.126.net/ljnSwA99K3idbLxT35O9gg==/109951165974133758.jpg","accountStatus":0,"gender":1,"city":230100,"birthday":0,"userId":110687265,"userType":0,"nickname":"在聆听吗","signature":"大象没有眼泪，可他却想要流泪","description":"","detailDescription":"","avatarImgId":109951165974133760,"backgroundImgId":109951165456573950,"backgroundUrl":"http://p1.music.126.net/oHNJ-lHiX1zwj-eDGqt7Vg==/109951165456573954.jpg","authority":0,"mutual":false,"expertTags":null,"experts":null,"djStatus":0,"vipType":11,"remarkName":null,"authenticationTypes":0,"avatarDetail":null,"avatarImgIdStr":"109951165974133758","backgroundImgIdStr":"109951165456573954","anchor":false,"avatarImgId_str":"109951165974133758"},{"defaultAvatar":false,"province":1000000,"authStatus":0,"followed":false,"avatarUrl":"http://p1.music.126.net/L8oV6RILZpUhm1XFtKQ5vQ==/109951163141347108.jpg","accountStatus":0,"gender":0,"city":1004900,"birthday":0,"userId":574000875,"userType":0,"nickname":"林羡鱼小姐","signature":"喜欢各种好听的声音。","description":"","detailDescription":"","avatarImgId":109951163141347100,"backgroundImgId":109951163098746080,"backgroundUrl":"http://p1.music.126.net/RuJBcHEgH7SmJGkKVpRvtg==/109951163098746078.jpg","authority":0,"mutual":false,"expertTags":null,"experts":null,"djStatus":0,"vipType":11,"remarkName":null,"authenticationTypes":0,"avatarDetail":null,"avatarImgIdStr":"109951163141347108","backgroundImgIdStr":"109951163098746078","anchor":false,"avatarImgId_str":"109951163141347108"}],"subscribed":false,"creator":{"defaultAvatar":false,"province":310000,"authStatus":0,"followed":false,"avatarUrl":"http://p1.music.126.net/dRf7W7t0MB6bzfYGjskwoA==/6017627139384597.jpg","accountStatus":0,"gender":1,"city":310101,"birthday":0,"userId":20226098,"userType":0,"nickname":"大藏藏","signature":"oh my international cool playboy!","description":"","detailDescription":"","avatarImgId":6017627139384597,"backgroundImgId":109951166202689170,"backgroundUrl":"http://p1.music.126.net/lt1K0huJagqDwbrmkUcYPA==/109951166202689168.jpg","authority":0,"mutual":false,"expertTags":null,"experts":null,"djStatus":0,"vipType":11,"remarkName":null,"authenticationTypes":0,"avatarDetail":null,"avatarImgIdStr":"6017627139384597","backgroundImgIdStr":"109951166202689168","anchor":false},"tracks":[{"name":"再.见","id":2006426342,"pst":0,"t":0,"ar":[{"id":11359,"name":"达达乐队","tns":[],"alias":[]}],"alia":[],"pop":45,"st":0,"rt":"","fee":8,"v":5,"crbt":null,"cf":"","al":{"id":156493852,"name":"Hello!","picUrl":"http://p2.music.126.net/RxhBtn2thzgATXNFGic14A==/109951168143989430.jpg","tns":[],"pic_str":"109951168143989430","pic":109951168143989420},"dt":297991,"h":{"br":320001,"fid":0,"size":11922329,"vd":-52793},"m":{"br":192001,"fid":0,"size":7153415,"vd":-50213},"l":{"br":128001,"fid":0,"size":4768958,"vd":-48547},"sq":{"br":945335,"fid":0,"size":35212722,"vd":-53498},"hr":null,"a":null,"cd":"01","no":8,"rtUrl":null,"ftype":0,"rtUrls":[],"djId":0,"copyright":0,"s_id":0,"mark":8192,"originCoverType":0,"originSongSimpleData":null,"tagPicList":null,"resourceState":true,"version":5,"songJumpInfo":null,"entertainmentTags":null,"awardTags":null,"single":0,"noCopyrightRcmd":null,"rtype":0,"rurl":null,"mst":9,"cp":2708533,"mv":0,"publishTime":0},{"name":"你朝我的方向走来","id":1345336667,"pst":0,"t":0,"ar":[{"id":4492,"name":"马念先","tns":[],"alias":[]},{"id":12285372,"name":"9m88","tns":[],"alias":[]}],"alia":[],"pop":85,"st":0,"rt":"","fee":1,"v":15,"crbt":null,"cf":"","al":{"id":75512731,"name":"你朝我的方向走来","picUrl":"http://p2.music.126.net/5b9MF77lAT4Y1R7YerJdDQ==/109951163854281036.jpg","tns":[],"pic_str":"109951163854281036","pic":109951163854281040},"dt":210348,"h":{"br":320000,"fid":0,"size":8416697,"vd":-41287},"m":{"br":192000,"fid":0,"size":5050035,"vd":-38692},"l":{"br":128000,"fid":0,"size":3366705,"vd":-37036},"sq":{"br":894188,"fid":0,"size":23511441,"vd":-41324},"hr":null,"a":null,"cd":"01","no":1,"rtUrl":null,"ftype":0,"rtUrls":[],"djId":0,"copyright":1,"s_id":0,"mark":8192,"originCoverType":1,"originSongSimpleData":null,"tagPicList":null,"resourceState":true,"version":15,"songJumpInfo":null,"entertainmentTags":null,"awardTags":null,"single":0,"noCopyrightRcmd":null,"rtype":0,"rurl":null,"mst":9,"cp":7002,"mv":0,"publishTime":1550073600000},{"name":"燃烧的爱情 feat.李鹏(反光镜)","id":1319891450,"pst":0,"t":0,"ar":[{"id":13056,"name":"闪星TwinkleStar","tns":[],"alias":[]}],"alia":[],"pop":35,"st":0,"rt":"","fee":8,"v":28,"crbt":null,"cf":"","al":{"id":74355954,"name":"《星火 TWINKLE IN THE DARK》","picUrl":"http://p2.music.126.net/Uz9XkA1gKxQJa7bnouULRw==/109951163661848704.jpg","tns":[],"pic_str":"109951163661848704","pic":109951163661848700},"dt":281419,"h":{"br":320000,"fid":0,"size":11259864,"vd":-66543},"m":{"br":192000,"fid":0,"size":6755936,"vd":-64006},"l":{"br":128000,"fid":0,"size":4503972,"vd":-62557},"sq":{"br":1020259,"fid":0,"size":35890172,"vd":-66536},"hr":null,"a":null,"cd":"01","no":4,"rtUrl":null,"ftype":0,"rtUrls":[],"djId":0,"copyright":2,"s_id":0,"mark":8192,"originCoverType":0,"originSongSimpleData":null,"tagPicList":null,"resourceState":true,"version":28,"songJumpInfo":null,"entertainmentTags":null,"awardTags":null,"single":0,"noCopyrightRcmd":null,"rtype":0,"rurl":null,"mst":9,"cp":0,"mv":10891936,"publishTime":1540279243096},{"name":"Love Is Love","id":1864902904,"pst":0,"t":0,"ar":[{"id":13104057,"name":"昨夜派对（L.N Party）","tns":[],"alias":[]}],"alia":[],"pop":95,"st":0,"rt":"","fee":8,"v":9,"crbt":null,"cf":"","al":{"id":131032126,"name":"Love Is Love","picUrl":"http://p2.music.126.net/y3lwXDguhKoOFfvrw_wBww==/109951166226373248.jpg","tns":[],"pic_str":"109951166226373248","pic":109951166226373250},"dt":234000,"h":{"br":320002,"fid":0,"size":9361965,"vd":-44521},"m":{"br":192002,"fid":0,"size":5617197,"vd":-41924},"l":{"br":128002,"fid":0,"size":3744813,"vd":-40094},"sq":{"br":862506,"fid":0,"size":25228324,"vd":-44515},"hr":{"br":1620341,"fid":0,"size":47394994,"vd":-44519},"a":null,"cd":"01","no":1,"rtUrl":null,"ftype":0,"rtUrls":[],"djId":0,"copyright":1,"s_id":0,"mark":537141248,"originCoverType":1,"originSongSimpleData":null,"tagPicList":null,"resourceState":true,"version":9,"songJumpInfo":null,"entertainmentTags":null,"awardTags":null,"single":0,"noCopyrightRcmd":null,"rtype":0,"rurl":null,"mst":9,"cp":0,"mv":0,"publishTime":1627833600000},{"name":"我们万岁","id":1323304980,"pst":0,"t":0,"ar":[{"id":2116,"name":"陈奕迅","tns":[],"alias":[]},{"id":14713083,"name":"eason and the duo band","tns":[],"alias":[]}],"alia":[],"pop":100,"st":0,"rt":null,"fee":1,"v":174,"crbt":null,"cf":"","al":{"id":74268947,"name":"L.O.V.E.","picUrl":"http://p2.music.126.net/n8objKMAfyw-cotbj9CmQw==/109951163676240009.jpg","tns":[],"pic_str":"109951163676240009","pic":109951163676240020},"dt":236638,"h":{"br":320000,"fid":0,"size":9467565,"vd":-42069},"m":{"br":192000,"fid":0,"size":5680557,"vd":-39512},"l":{"br":128000,"fid":0,"size":3787053,"vd":-37935},"sq":{"br":956568,"fid":0,"size":28295169,"vd":-41932},"hr":{"br":1723168,"fid":0,"size":50971063,"vd":-42041},"a":null,"cd":"01","no":12,"rtUrl":null,"ftype":0,"rtUrls":[],"djId":0,"copyright":2,"s_id":0,"mark":536879104,"originCoverType":1,"originSongSimpleData":null,"tagPicList":null,"resourceState":true,"version":174,"songJumpInfo":null,"entertainmentTags":null,"awardTags":null,"single":0,"noCopyrightRcmd":null,"rtype":0,"rurl":null,"mst":9,"cp":7003,"mv":10785699,"publishTime":1542556800007},{"name":"最佳损友","id":65800,"pst":0,"t":0,"ar":[{"id":2116,"name":"陈奕迅","tns":[],"alias":[]}],"alia":[],"pop":100,"st":0,"rt":"600902000005377598","fee":8,"v":451,"crbt":null,"cf":"","al":{"id":6452,"name":"Life Continues…","picUrl":"http://p2.music.126.net/AAKrMZu-zyunLRqAMO9JlA==/109951166577890720.jpg","tns":[],"pic_str":"109951166577890720","pic":109951166577890720},"dt":233560,"h":{"br":320000,"fid":0,"size":9344566,"vd":-27575},"m":{"br":192000,"fid":0,"size":5606757,"vd":-24974},"l":{"br":128000,"fid":0,"size":3737853,"vd":-23218},"sq":{"br":862262,"fid":0,"size":25173762,"vd":-28243},"hr":null,"a":null,"cd":"1","no":3,"rtUrl":null,"ftype":0,"rtUrls":[],"djId":0,"copyright":1,"s_id":0,"mark":8192,"originCoverType":1,"originSongSimpleData":null,"tagPicList":null,"resourceState":true,"version":451,"songJumpInfo":null,"entertainmentTags":null,"awardTags":null,"single":0,"noCopyrightRcmd":null,"rtype":0,"rurl":null,"mst":9,"cp":7003,"mv":303142,"publishTime":1136044800000},{"name":"再见 (Live)","id":1473544948,"pst":0,"t":0,"ar":[{"id":11359,"name":"达达乐队","tns":[],"alias":[]}],"alia":[],"pop":25,"st":0,"rt":"","fee":1,"v":12,"crbt":null,"cf":"","al":{"id":94403609,"name":"乐队的夏天2 第8期","picUrl":"http://p2.music.126.net/UXzJRy6YTqR6ABpvQATrhg==/109951165264574088.jpg","tns":[],"pic_str":"109951165264574088","pic":109951165264574080},"dt":245728,"h":{"br":320000,"fid":0,"size":9831405,"vd":-44037},"m":{"br":192000,"fid":0,"size":5898861,"vd":-41426},"l":{"br":128000,"fid":0,"size":3932589,"vd":-39797},"sq":{"br":944749,"fid":0,"size":29018919,"vd":-44060},"hr":{"br":1713369,"fid":0,"size":52627846,"vd":-44018},"a":null,"cd":"01","no":4,"rtUrl":null,"ftype":0,"rtUrls":[],"djId":0,"copyright":0,"s_id":0,"mark":536944640,"originCoverType":2,"originSongSimpleData":{"songId":185726,"name":"再见","artists":[{"id":6453,"name":"张震岳"}],"albumMeta":{"id":18881,"name":"再见"}},"tagPicList":null,"resourceState":true,"version":12,"songJumpInfo":null,"entertainmentTags":null,"awardTags":null,"single":0,"noCopyrightRcmd":null,"rtype":0,"rurl":null,"mst":9,"cp":2711491,"mv":0,"publishTime":0}],"videoIds":null,"videos":null,"trackIds":[{"id":2006426342,"v":6,"t":0,"at":1690219429768,"alg":null,"uid":334095530,"rcmdReason":"","sc":null,"f":null,"sr":null},{"id":1345336667,"v":16,"t":0,"at":1690219387714,"alg":null,"uid":334095530,"rcmdReason":"","sc":null,"f":null,"sr":null},{"id":1319891450,"v":29,"t":0,"at":1690219360469,"alg":null,"uid":334095530,"rcmdReason":"","sc":null,"f":null,"sr":null},{"id":1864902904,"v":10,"t":0,"at":1690203864878,"alg":null,"uid":474989529,"rcmdReason":"","sc":null,"f":null,"sr":null},{"id":1323304980,"v":175,"t":0,"at":1690203800780,"alg":null,"uid":474989529,"rcmdReason":"","sc":null,"f":null,"sr":null},{"id":65800,"v":452,"t":0,"at":1690203790280,"alg":null,"uid":474989529,"rcmdReason":"","sc":null,"f":null,"sr":null},{"id":1473544948,"v":13,"t":0,"at":1690203477050,"alg":null,"uid":296658058,"rcmdReason":"","sc":null,"f":null,"sr":null}],"bannedTrackIds":null,"mvResourceInfos":null,"shareCount":8,"commentCount":197,"remixVideo":null,"sharedUsers":[{"defaultAvatar":false,"province":110000,"authStatus":0,"followed":false,"avatarUrl":"http://p1.music.126.net/YiCVHfj_d1iOtIz_RUYEsg==/109951165423851551.jpg","accountStatus":0,"gender":2,"city":110107,"birthday":0,"userId":296658058,"userType":0,"nickname":"吼吼破喉咙","signature":"一面笑的天真无邪，一面看破一切……","description":"","detailDescription":"","avatarImgId":109951165423851550,"backgroundImgId":2002210674180202,"backgroundUrl":"http://p1.music.126.net/pmHS4fcQtcNEGewNb5HRhg==/2002210674180202.jpg","authority":0,"mutual":false,"expertTags":null,"experts":null,"djStatus":0,"vipType":11,"remarkName":null,"authenticationTypes":0,"avatarDetail":null,"avatarImgIdStr":"109951165423851551","backgroundImgIdStr":"2002210674180202","anchor":false,"avatarImgId_str":"109951165423851551"},{"defaultAvatar":false,"province":310000,"authStatus":0,"followed":false,"avatarUrl":"http://p1.music.126.net/68tP-It60UcojJ8YLtpEgA==/109951166889326808.jpg","accountStatus":0,"gender":0,"city":310101,"birthday":0,"userId":3267498124,"userType":0,"nickname":"Fiona有理想","signature":"","description":"","detailDescription":"","avatarImgId":109951166889326820,"backgroundImgId":109951162868126480,"backgroundUrl":"http://p1.music.126.net/_f8R60U9mZ42sSNvdPn2sQ==/109951162868126486.jpg","authority":0,"mutual":false,"expertTags":null,"experts":null,"djStatus":0,"vipType":11,"remarkName":null,"authenticationTypes":0,"avatarDetail":null,"avatarImgIdStr":"109951166889326808","backgroundImgIdStr":"109951162868126486","anchor":false,"avatarImgId_str":"109951166889326808"},{"defaultAvatar":false,"province":440000,"authStatus":0,"followed":false,"avatarUrl":"http://p1.music.126.net/7S8ItIxy286xgWQYGyWL_Q==/109951168750137278.jpg","accountStatus":0,"gender":1,"city":440100,"birthday":0,"userId":334095530,"userType":0,"nickname":"啃啃坑坑","signature":"","description":"","detailDescription":"","avatarImgId":109951168750137280,"backgroundImgId":109951166302133100,"backgroundUrl":"http://p1.music.126.net/aCjLbTGRioSk9MIwLuYlwg==/109951166302133107.jpg","authority":0,"mutual":false,"expertTags":null,"experts":null,"djStatus":0,"vipType":11,"remarkName":null,"authenticationTypes":0,"avatarDetail":null,"avatarImgIdStr":"109951168750137278","backgroundImgIdStr":"109951166302133107","anchor":false,"avatarImgId_str":"109951168750137278"}],"historySharedUsers":[{"defaultAvatar":false,"province":0,"authStatus":0,"followed":false,"avatarUrl":"http://p1.music.126.net/3lGG_EqUjGO6Gt_0XBTEbA==/109951165671366718.jpg","accountStatus":0,"gender":0,"city":0,"birthday":0,"userId":474989529,"userType":0,"nickname":"LongDreamRiver","signature":null,"description":null,"detailDescription":null,"avatarImgId":0,"backgroundImgId":0,"backgroundUrl":null,"authority":0,"mutual":false,"expertTags":null,"experts":null,"djStatus":0,"vipType":0,"remarkName":null,"authenticationTypes":0,"avatarDetail":null,"avatarImgIdStr":"0","backgroundImgIdStr":"0","anchor":false}],"gradeStatus":"NONE","score":null,"algTags":null},"urls":null,"privileges":[{"id":2006426342,"fee":8,"payed":1,"realPayed":0,"st":0,"pl":999000,"dl":999000,"sp":7,"cp":1,"subp":1,"cs":false,"maxbr":999000,"fl":128000,"pc":null,"toast":false,"flag":260,"paidBigBang":false,"preSell":false,"playMaxbr":999000,"downloadMaxbr":999000,"maxBrLevel":"lossless","playMaxBrLevel":"lossless","downloadMaxBrLevel":"lossless","plLevel":"lossless","dlLevel":"lossless","flLevel":"standard","rscl":null,"freeTrialPrivilege":{"resConsumable":false,"userConsumable":false,"listenType":null,"cannotListenReason":null},"rightSource":0,"chargeInfoList":[{"rate":128000,"chargeUrl":null,"chargeMessage":null,"chargeType":0},{"rate":192000,"chargeUrl":null,"chargeMessage":null,"chargeType":1},{"rate":320000,"chargeUrl":null,"chargeMessage":null,"chargeType":1},{"rate":999000,"chargeUrl":null,"chargeMessage":null,"chargeType":1}]},{"id":1345336667,"fee":1,"payed":1,"realPayed":0,"st":0,"pl":999000,"dl":999000,"sp":7,"cp":1,"subp":1,"cs":false,"maxbr":999000,"fl":0,"pc":null,"toast":false,"flag":260,"paidBigBang":false,"preSell":false,"playMaxbr":999000,"downloadMaxbr":999000,"maxBrLevel":"lossless","playMaxBrLevel":"lossless","downloadMaxBrLevel":"lossless","plLevel":"lossless","dlLevel":"lossless","flLevel":"none","rscl":null,"freeTrialPrivilege":{"resConsumable":false,"userConsumable":false,"listenType":null,"cannotListenReason":null},"rightSource":0,"chargeInfoList":[{"rate":128000,"chargeUrl":null,"chargeMessage":null,"chargeType":1},{"rate":192000,"chargeUrl":null,"chargeMessage":null,"chargeType":1},{"rate":320000,"chargeUrl":null,"chargeMessage":null,"chargeType":1},{"rate":999000,"chargeUrl":null,"chargeMessage":null,"chargeType":1}]},{"id":1319891450,"fee":8,"payed":1,"realPayed":0,"st":0,"pl":999000,"dl":999000,"sp":7,"cp":1,"subp":1,"cs":false,"maxbr":999000,"fl":128000,"pc":null,"toast":false,"flag":260,"paidBigBang":false,"preSell":false,"playMaxbr":999000,"downloadMaxbr":999000,"maxBrLevel":"lossless","playMaxBrLevel":"lossless","downloadMaxBrLevel":"lossless","plLevel":"lossless","dlLevel":"lossless","flLevel":"standard","rscl":null,"freeTrialPrivilege":{"resConsumable":false,"userConsumable":false,"listenType":null,"cannotListenReason":null},"rightSource":0,"chargeInfoList":[{"rate":128000,"chargeUrl":null,"chargeMessage":null,"chargeType":0},{"rate":192000,"chargeUrl":null,"chargeMessage":null,"chargeType":1},{"rate":320000,"chargeUrl":null,"chargeMessage":null,"chargeType":1},{"rate":999000,"chargeUrl":null,"chargeMessage":null,"chargeType":1}]},{"id":1864902904,"fee":8,"payed":1,"realPayed":0,"st":0,"pl":999000,"dl":999000,"sp":7,"cp":1,"subp":1,"cs":false,"maxbr":999000,"fl":128000,"pc":null,"toast":false,"flag":4,"paidBigBang":false,"preSell":false,"playMaxbr":999000,"downloadMaxbr":999000,"maxBrLevel":"hires","playMaxBrLevel":"hires","downloadMaxBrLevel":"hires","plLevel":"hires","dlLevel":"hires","flLevel":"standard","rscl":null,"freeTrialPrivilege":{"resConsumable":false,"userConsumable":false,"listenType":null,"cannotListenReason":null},"rightSource":0,"chargeInfoList":[{"rate":128000,"chargeUrl":null,"chargeMessage":null,"chargeType":0},{"rate":192000,"chargeUrl":null,"chargeMessage":null,"chargeType":1},{"rate":320000,"chargeUrl":null,"chargeMessage":null,"chargeType":1},{"rate":999000,"chargeUrl":null,"chargeMessage":null,"chargeType":1},{"rate":1999000,"chargeUrl":null,"chargeMessage":null,"chargeType":1}]},{"id":1323304980,"fee":1,"payed":1,"realPayed":0,"st":0,"pl":999000,"dl":999000,"sp":7,"cp":1,"subp":1,"cs":false,"maxbr":999000,"fl":0,"pc":null,"toast":false,"flag":260,"paidBigBang":false,"preSell":false,"playMaxbr":999000,"downloadMaxbr":999000,"maxBrLevel":"hires","playMaxBrLevel":"hires","downloadMaxBrLevel":"hires","plLevel":"hires","dlLevel":"hires","flLevel":"none","rscl":null,"freeTrialPrivilege":{"resConsumable":false,"userConsumable":false,"listenType":null,"cannotListenReason":null},"rightSource":0,"chargeInfoList":[{"rate":128000,"chargeUrl":null,"chargeMessage":null,"chargeType":1},{"rate":192000,"chargeUrl":null,"chargeMessage":null,"chargeType":1},{"rate":320000,"chargeUrl":null,"chargeMessage":null,"chargeType":1},{"rate":999000,"chargeUrl":null,"chargeMessage":null,"chargeType":1},{"rate":1999000,"chargeUrl":null,"chargeMessage":null,"chargeType":1}]},{"id":65800,"fee":8,"payed":1,"realPayed":0,"st":0,"pl":999000,"dl":999000,"sp":7,"cp":1,"subp":1,"cs":false,"maxbr":999000,"fl":128000,"pc":null,"toast":false,"flag":260,"paidBigBang":false,"preSell":false,"playMaxbr":999000,"downloadMaxbr":999000,"maxBrLevel":"lossless","playMaxBrLevel":"lossless","downloadMaxBrLevel":"lossless","plLevel":"lossless","dlLevel":"lossless","flLevel":"standard","rscl":null,"freeTrialPrivilege":{"resConsumable":false,"userConsumable":false,"listenType":null,"cannotListenReason":null},"rightSource":0,"chargeInfoList":[{"rate":128000,"chargeUrl":null,"chargeMessage":null,"chargeType":0},{"rate":192000,"chargeUrl":null,"chargeMessage":null,"chargeType":1},{"rate":320000,"chargeUrl":null,"chargeMessage":null,"chargeType":1},{"rate":999000,"chargeUrl":null,"chargeMessage":null,"chargeType":1}]},{"id":1473544948,"fee":1,"payed":1,"realPayed":0,"st":0,"pl":999000,"dl":999000,"sp":7,"cp":1,"subp":1,"cs":false,"maxbr":999000,"fl":0,"pc":null,"toast":false,"flag":4,"paidBigBang":false,"preSell":false,"playMaxbr":999000,"downloadMaxbr":999000,"maxBrLevel":"hires","playMaxBrLevel":"hires","downloadMaxBrLevel":"hires","plLevel":"hires","dlLevel":"hires","flLevel":"none","rscl":null,"freeTrialPrivilege":{"resConsumable":false,"userConsumable":false,"listenType":null,"cannotListenReason":null},"rightSource":0,"chargeInfoList":[{"rate":128000,"chargeUrl":null,"chargeMessage":null,"chargeType":1},{"rate":192000,"chargeUrl":null,"chargeMessage":null,"chargeType":1},{"rate":320000,"chargeUrl":null,"chargeMessage":null,"chargeType":1},{"rate":999000,"chargeUrl":null,"chargeMessage":null,"chargeType":1},{"rate":1999000,"chargeUrl":null,"chargeMessage":null,"chargeType":1}]}],"sharedPrivilege":{"status":"SHARED","usePermission":"NORMAL"},"resEntrance":null,"fromUsers":null,"fromUserCount":0,"songFromUsers":null,"trialMode":11}